LICENSE
README.md
setup.cfg
setup.py
nps_sdk/__init__.py
nps_sdk/configuration.py
nps_sdk/constants.py
nps_sdk/errors.py
nps_sdk/file_adapter.py
nps_sdk/sdk.py
nps_sdk/services.py
nps_sdk/soap_client.py
nps_sdk/utils.py
nps_sdk/version.py
nps_sdk.egg-info/PKG-INFO
nps_sdk.egg-info/SOURCES.txt
nps_sdk.egg-info/dependency_links.txt
nps_sdk.egg-info/requires.txt
nps_sdk.egg-info/top_level.txt
nps_sdk/certs/__init__.py
nps_sdk/conf/__init__.py
nps_sdk/conf/sanititize_struc.py
nps_sdk/wsdl/__init__.py
nps_sdk/wsdl/development.wsdl
nps_sdk/wsdl/production.wsdl
nps_sdk/wsdl/sandbox.wsdl
nps_sdk/wsdl/staging.wsdl
test/__init__.py
test/cielo3_examples.py
test/examples.py
test/get_session.py
test/mops_test.py
test/test.py